colorswan/__init__.py
colorswan/constants.py
colorswan/okcolor.py
colorswan-0.2.0.dist-info/licenses/LICENSE
colorswan-0.2.0.dist-info/METADATA
colorswan-0.2.0.dist-info/WHEEL
colorswan-0.2.0.dist-info/top_level.txt
colorswan-0.2.0.dist-info/RECORD
