Metadata-Version: 2.4
Name: colorswan
Version: 0.2.0
Summary: Precision color conversion library (sRGB to Oklab/Oklch)
Author-email: Worod Haiadry <worod.h@gmail.com>
Project-URL: Homepage, https://github.com/worodh/colorswan
Classifier: Programming Language :: Python :: 3
Classifier: License :: OSI Approved :: MIT License
Classifier: Operating System :: OS Independent
Requires-Python: >=3.7
License-File: LICENSE
Dynamic: license-file
